distributions/Binomialdistribution.py
distributions/Gaussiandistribution.py
distributions/Generaldistribution.py
distributions/__init__.py
distributions_udacity_akshayudayahegde-0.1.0.dist-info/DESCRIPTION.rst
distributions_udacity_akshayudayahegde-0.1.0.dist-info/METADATA
distributions_udacity_akshayudayahegde-0.1.0.dist-info/RECORD
distributions_udacity_akshayudayahegde-0.1.0.dist-info/WHEEL
distributions_udacity_akshayudayahegde-0.1.0.dist-info/metadata.json
distributions_udacity_akshayudayahegde-0.1.0.dist-info/top_level.txt
