Metadata-Version: 2.0
Name: distributions-udacity-akshayudayahegde
Version: 0.1.0
Summary: Gaussian and Binomial Distribution Basic Functions
Home-page: UNKNOWN
Author: Akshay Udaya Hegde
Author-email: akshayudayhegde2@gmail.com
License: UNKNOWN
Platform: UNKNOWN
Classifier: Programming Language :: Python :: 3
Classifier: License :: OSI Approved :: MIT License
Classifier: Operating System :: OS Independent
